{
  "id": "MCF-2288",
  "parent_id": "MCF-2281",
  "title": "Each CAR MODEL VARIANT in the list contains the primary information",
  "description": "Each CAR MODEL VARIANT has multiple properties. Some of them are categorized as 'primary information' to signal a higher importance. Only those should be shown in each list item. They are documented in the CAR MODEL VARIANT epic (MCF-???).\n",
  "release_version": "2.1.0",
  "created_at": "2026-05-17T11:37:31.173+0200",
  "updated_at": "2026-05-31T16:40:57.488+0200"
}
