{
  "id": "MCF-505",
  "parent_id": "MCF-504",
  "title": "The RACING SERIES detail page contains a section with all connected IMAGES",
  "description": "The IMAGES are classified as secondary information. Therefore the section has to be positioned after all the primary information (lead image, primary relationship, etc.). It is displayed in list form, analog to list on the overview page.\n",
  "release_version": "0.6.0",
  "created_at": "2026-01-29T19:00:25.499+0100",
  "updated_at": "2026-01-29T19:39:15.449+0100"
}
