{
  "id": "MCF-1520",
  "parent_id": "MCF-22",
  "title": "PROGRAMME EPISODE detail page » Successor",
  "user_story": "As a visitor\nI want the PROGRAMME EPISODE detail page to show the connected PROGRAMME EPISODE\nSo I can ...\n",
  "description": "* The PROGRAMME EPISODE detail page is extended to contain a section for the connected PROGRAMME EPISODE.\n* The PROGRAMME EPISODE is presented with its name and primary information.\n* The PROGRAMME EPISODE contains a link to its detail page.\n* The PROGRAMME EPISODE has a thumbnail image.\n* When there is no PROGRAMME EPISODE connected to the PROGRAMME EPISODE then the section is not displayed at all.\n",
  "api_path": null,
  "response_options": [
    "N/A"
  ],
  "release_versions": [
    "0.10.0"
  ],
  "created_at": "2026-03-15T18:19:17.253+0100",
  "updated_at": "2026-03-17T11:45:21.510+0100"
}
